datawriter/__init__.py
datawriter/datawriter.py
datawriter-0.0.4.dist-info/LICENSE
datawriter-0.0.4.dist-info/METADATA
datawriter-0.0.4.dist-info/WHEEL
datawriter-0.0.4.dist-info/top_level.txt
datawriter-0.0.4.dist-info/RECORD
