Metadata-Version: 2.1
Name: datawriter
Version: 0.0.4
Summary: For logging collected data in a filetype of choice
Author: Alex Lewis
Author-email: alexscottlewis@gmail.com
Keywords: python,first package
Classifier: Development Status :: 3 - Alpha
Classifier: Intended Audience :: Education
Classifier: Programming Language :: Python :: 2
Classifier: Programming Language :: Python :: 3
Classifier: Operating System :: MacOS :: MacOS X
Classifier: Operating System :: Microsoft :: Windows
License-File: LICENSE
Requires-Dist: pandas
